HW4/q3/q32.vhd
library IEEE;
use IEEE.STD_LOGIC_1164.ALL;
USE ieee.numeric_std.ALL;
use ieee.std_logic_arith.all;

entity q32 is
    Port ( 
        clk, reset, inp : in std_logic;
        outMoore        : out std_logic
        );
end q32;

architecture Behavioral of q32 is
TYPE state IS (S0, S1, S2, S3, S4); 
SIGNAL Moore_state: state;
begin
PROCESS (clk, reset)
begin
    IF (reset = '1') THEN
        Moore_state <= S0;
    ELSIF (clk'event AND clk='1') THEN
        CASE Moore_state IS
        WHEN S0 =>
            IF inp = '1' THEN 
                Moore_state <= S1; 
            ELSE
                Moore_state <= S0;
            END IF;
        WHEN S1 =>
            IF inp = '1' THEN 
                Moore_state <= S2; 
            ELSE
                Moore_state <= S0; 
            END IF;
        WHEN S2 =>
            IF inp = '1' THEN
                Moore_state <= S3; 
            ELSE 
                Moore_state <= S0; 
            END IF;
        WHEN S3 =>
            IF inp = '1' THEN
                Moore_state <= S3; 
            ELSE 
                Moore_state <= S4; 
            END IF;
        WHEN S4 =>
            IF inp = '1' THEN
                Moore_state <= S1; 
            ELSE 
                Moore_state <= S0; 
            END IF;
        END CASE;
    END IF;
END PROCESS;

outMoore <= '1' WHEN Moore_state = S4 ELSE '0';

end Behavioral;

HW4/q3/test32.vhd
library IEEE;
use IEEE.NUMERIC_STD.ALL;
use IEEE.STD_LOGIC_1164.ALL;

entity Test32 is
end Test32;

architecture testbench of Test32 is  
    component q32 is
        Port ( 
            clk, reset, inp : in std_logic;
            outMoore        : out std_logic
        );
    end component;

    signal clk, reset, inp : std_logic;
    signal outMoore        : std_logic;
    constant CLK_PERIOD    : time := 10 ns;
begin
    cal : q32 port map (clk => clk, reset => reset, inp => inp, outMoore => outMoore);

    clk_process : process
    begin
        while now < 1000 ns loop 
            clk <= '0';
            wait for CLK_PERIOD / 2;
            clk <= '1';
            wait for CLK_PERIOD / 2;
        end loop;
        wait;
    end process;

    process is
    begin
        reset <= '1';
        wait for CLK_PERIOD;
        reset <= '0';

        inp <= '1';
        wait for CLK_PERIOD;
        inp <= '1';
        wait for CLK_PERIOD;
        inp <= '1';
        wait for CLK_PERIOD;
        inp <= '0';
        wait for CLK_PERIOD;
        inp <= '1';
        wait for CLK_PERIOD;
        inp <= '1';
        wait for CLK_PERIOD;
        inp <= '1';
        wait for CLK_PERIOD;
        inp <= '1';
        wait for CLK_PERIOD;
        inp <= '0';
        wait for CLK_PERIOD;

        wait;

    end process;
end testbench;

HW4/q3/out.vcd
$date
  Mon Jun 19 23:11:56 2023
$end
$version
  GHDL v0
$end
$timescale
  1 fs
$end
$scope module standard $end
$upscope $end
$scope module std_logic_1164 $end
$upscope $end
$scope module numeric_std $end
$upscope $end
$scope module std_logic_arith $end
$upscope $end
$scope module test32 $end
$var reg 1 ! clk $end
$var reg 1 " reset $end
$var reg 1 # inp $end
$var reg 1 $ outmoore $end
$scope module cal $end
$var reg 1 % clk $end
$var reg 1 & reset $end
$var reg 1 ' inp $end
$var reg 1 ( outmoore $end
$comment moore_state is not handled $end
$upscope $end
$upscope $end
$enddefinitions $end
#0
0!
1"
U#
0$
0%
1&
U'
0(
#5000000
1!
1%
#10000000
0!
0"
1#
0%
0&
1'
#15000000
1!
1%
#20000000
0!
0%
#25000000
1!
1%
#30000000
0!
0%
#35000000
1!
1%
#40000000
0!
0#
0%
0'
#45000000
1!
1$
1%
1(
#50000000
0!
1#
0%
1'
#55000000
1!
0$
1%
0(
#60000000
0!
0%
#65000000
1!
1%
#70000000
0!
0%
#75000000
1!
1%
#80000000
0!
0%
#85000000
1!
1%
#90000000
0!
0#
0%
0'
#95000000
1!
1$
1%
1(
#100000000
0!
0%
#105000000
1!
0$
1%
0(
