HW4/q1/q1all.vhdl
library IEEE;
use IEEE.STD_LOGIC_1164.ALL;
USE ieee.numeric_std.ALL;

entity q1 is
    generic(
        n : integer := 8 
    );
    Port ( 
        clk, reset        : in std_logic;
        inp               : in std_logic_vector(n - 1 downto 0);
        start_index_fisrt : out std_logic_vector(n / 2 downto 0);
        last_index_first  : out std_logic_vector(n / 2 downto 0);
        start_index_end   : out std_logic_vector(n / 2 downto 0);
        last_index_end    : out std_logic_vector(n / 2 downto 0)
        );
end q1;

architecture Behavioral of q1 is
    TYPE state IS (S0, S1, S2, S3, S4); 
    SIGNAL states: state;
begin
PROCESS (clk, reset)
    variable count : integer := 0;
begin
    IF (clk'event AND clk='1') THEN
        IF (reset = '1' or count = n) THEN
            states <= S0;
            count := 0;
        ElSE
            CASE states IS
            WHEN S0 =>
                IF inp(count) = '1' THEN 
                    states <= S1;
                ELSE
                    states <= S0;
                END IF;
            WHEN S1 =>
                IF inp(count) = '1' THEN 
                    states <= S1;
                ELSE
                    states <= S2;
                    start_index_fisrt <= std_logic_vector(to_unsigned(count + 1, n / 2 + 1)); 
                    last_index_first <= std_logic_vector(to_unsigned(count + 1, n / 2 + 1)); 
                END IF;
            WHEN S2 =>
                IF inp(count) = '1' THEN
                    states <= S3; 
                ELSE 
                    states <= S2; 
                    last_index_first <= std_logic_vector(to_unsigned(count + 1, n / 2 + 1)); 
                END IF;
            WHEN S3 =>
                IF inp(count) = '1' THEN
                    states <= S3; 
                ELSE 
                    states <= S4; 
                    start_index_end <= std_logic_vector(to_unsigned(count + 1, n / 2 + 1)); 
                    last_index_end <= std_logic_vector(to_unsigned(count + 1, n / 2 + 1)); 
                END IF;
            WHEN S4 =>
                IF inp(count) = '1' THEN
                    states <= S3; 
                ELSE 
                    states <= S4; 
                    last_index_end <= std_logic_vector(to_unsigned(count + 1, n / 2 + 1)); 
                END IF;
            END CASE;
            count := count + 1;
        END IF;
    END if;
END PROCESS;
end Behavioral;

library IEEE;
use IEEE.NUMERIC_STD.ALL;
use IEEE.STD_LOGIC_1164.ALL;

entity Test1 is
    generic(
        n : integer := 8 
    );
end Test1;

architecture testbench of Test1 is  
    component q1 is
        Port ( 
            clk, reset        : in std_logic;
            inp               : in std_logic_vector(n - 1 downto 0);
            start_index_fisrt : out std_logic_vector(n / 2 downto 0);
            last_index_first  : out std_logic_vector(n / 2 downto 0);
            start_index_end   : out std_logic_vector(n / 2 downto 0);
            last_index_end    : out std_logic_vector(n / 2 downto 0)
        );
    end component;

    signal clk, reset        : std_logic;
    signal inp               : std_logic_vector(n - 1 downto 0);
    signal start_index_fisrt : std_logic_vector(n / 2 downto 0);
    signal last_index_first  : std_logic_vector(n / 2 downto 0);
    signal start_index_end   : std_logic_vector(n / 2 downto 0);
    signal last_index_end    : std_logic_vector(n / 2 downto 0);

    constant CLK_PERIOD    : time := 10 ns;
begin
    cal : q1 port map (clk => clk, reset => reset, inp => inp, start_index_fisrt => start_index_fisrt, last_index_first => last_index_first, start_index_end => start_index_end, last_index_end => last_index_end);

    clk_process : process
    begin
        while now < 1000 ns loop 
            clk <= '0';
            wait for CLK_PERIOD / 2;
            clk <= '1';
            wait for CLK_PERIOD / 2;
        end loop;
        wait;
    end process;

    process is
    begin
        reset <= '1';
        wait for CLK_PERIOD;
        reset <= '0';

        inp <= "01001010";
        wait for 100 ns;
        wait;

    end process;
end testbench;

HW4/q1/out.vcd
$date
  Fri Jun 23 17:03:11 2023
$end
$version
  GHDL v0
$end
$timescale
  1 fs
$end
$scope module standard $end
$upscope $end
$scope module std_logic_1164 $end
$upscope $end
$scope module numeric_std $end
$upscope $end
$scope module test1 $end
$var reg 1 ! clk $end
$var reg 1 " reset $end
$var reg 8 # inp[7:0] $end
$var reg 5 $ start_index_fisrt[4:0] $end
$var reg 5 % last_index_first[4:0] $end
$var reg 5 & start_index_end[4:0] $end
$var reg 5 ' last_index_end[4:0] $end
$scope module cal $end
$var reg 1 ( clk $end
$var reg 1 ) reset $end
$var reg 8 * inp[7:0] $end
$var reg 5 + start_index_fisrt[4:0] $end
$var reg 5 , last_index_first[4:0] $end
$var reg 5 - start_index_end[4:0] $end
$var reg 5 . last_index_end[4:0] $end
$comment states is not handled $end
$upscope $end
$upscope $end
$enddefinitions $end
#0
0!
1"
bUUUUUUUU #
bUUUUU $
bUUUUU %
bUUUUU &
bUUUUU '
0(
1)
bUUUUUUUU *
bUUUUU +
bUUUUU ,
bUUUUU -
bUUUUU .
#5000000
1!
1(
#10000000
0!
0"
b01000101 #
0(
0)
b01000101 *
#15000000
1!
1(
#20000000
0!
0(
#25000000
1!
b00010 $
b00010 %
1(
b00010 +
b00010 ,
#30000000
0!
0(
#35000000
1!
1(
#40000000
0!
0(
#45000000
1!
b00100 &
b00100 '
1(
b00100 -
b00100 .
#50000000
0!
0(
#55000000
1!
b00101 '
1(
b00101 .
#60000000
0!
0(
#65000000
1!
b00110 '
1(
b00110 .
#70000000
0!
0(
#75000000
1!
1(
#80000000
0!
0(
#85000000
1!
b01000 &
b01000 '
1(
b01000 -
b01000 .
#90000000
0!
0(
#95000000
1!
1(
#100000000
0!
0(
#105000000
1!
1(
#110000000
0!
0(
#115000000
1!
1(
#120000000
0!
0(
#125000000
1!
1(
#130000000
0!
0(
#135000000
1!
b00100 &
b00100 '
1(
b00100 -
b00100 .
#140000000
0!
0(
#145000000
1!
b00101 '
1(
b00101 .
#150000000
0!
0(
#155000000
1!
b00110 '
1(
b00110 .
#160000000
0!
0(
#165000000
1!
1(
#170000000
0!
0(
#175000000
1!
b01000 &
b01000 '
1(
b01000 -
b01000 .
#180000000
0!
0(
#185000000
1!
1(
#190000000
0!
0(
#195000000
1!
1(
#200000000
0!
0(
#205000000
1!
1(
#210000000
0!
0(
#215000000
1!
1(
#220000000
0!
0(
#225000000
1!
b00100 &
b00100 '
1(
b00100 -
b00100 .
#230000000
0!
0(
#235000000
1!
b00101 '
1(
b00101 .
#240000000
0!
0(
#245000000
1!
b00110 '
1(
b00110 .
#250000000
0!
0(
#255000000
1!
1(
#260000000
0!
0(
#265000000
1!
b01000 &
b01000 '
1(
b01000 -
b01000 .
#270000000
0!
0(
#275000000
1!
1(
#280000000
0!
0(
#285000000
1!
1(
#290000000
0!
0(
#295000000
1!
1(
#300000000
0!
0(
#305000000
1!
1(
#310000000
0!
0(
#315000000
1!
b00100 &
b00100 '
1(
b00100 -
b00100 .
#320000000
0!
0(
#325000000
1!
b00101 '
1(
b00101 .
#330000000
0!
0(
#335000000
1!
b00110 '
1(
b00110 .
#340000000
0!
0(
#345000000
1!
1(
#350000000
0!
0(
#355000000
1!
b01000 &
b01000 '
1(
b01000 -
b01000 .
#360000000
0!
0(
#365000000
1!
1(
#370000000
0!
0(
#375000000
1!
1(
#380000000
0!
0(
#385000000
1!
1(
#390000000
0!
0(
#395000000
1!
1(
#400000000
0!
0(
#405000000
1!
b00100 &
b00100 '
1(
b00100 -
b00100 .
#410000000
0!
0(
#415000000
1!
b00101 '
1(
b00101 .
#420000000
0!
0(
#425000000
1!
b00110 '
1(
b00110 .
#430000000
0!
0(
#435000000
1!
1(
#440000000
0!
0(
#445000000
1!
b01000 &
b01000 '
1(
b01000 -
b01000 .
#450000000
0!
0(
#455000000
1!
1(
#460000000
0!
0(
#465000000
1!
1(
#470000000
0!
0(
#475000000
1!
1(
#480000000
0!
0(
#485000000
1!
1(
#490000000
0!
0(
#495000000
1!
b00100 &
b00100 '
1(
b00100 -
b00100 .
#500000000
0!
0(
#505000000
1!
b00101 '
1(
b00101 .
#510000000
0!
0(
#515000000
1!
b00110 '
1(
b00110 .
#520000000
0!
0(
#525000000
1!
1(
#530000000
0!
0(
#535000000
1!
b01000 &
b01000 '
1(
b01000 -
b01000 .
#540000000
0!
0(
#545000000
1!
1(
#550000000
0!
0(
#555000000
1!
1(
#560000000
0!
0(
#565000000
1!
1(
#570000000
0!
0(
#575000000
1!
1(
#580000000
0!
0(
#585000000
1!
b00100 &
b00100 '
1(
b00100 -
b00100 .
#590000000
0!
0(
#595000000
1!
b00101 '
1(
b00101 .
#600000000
0!
0(
#605000000
1!
b00110 '
1(
b00110 .
#610000000
0!
0(
#615000000
1!
1(
#620000000
0!
0(
#625000000
1!
b01000 &
b01000 '
1(
b01000 -
b01000 .
#630000000
0!
0(
#635000000
1!
1(
#640000000
0!
0(
#645000000
1!
1(
#650000000
0!
0(
#655000000
1!
1(
#660000000
0!
0(
#665000000
1!
1(
#670000000
0!
0(
#675000000
1!
b00100 &
b00100 '
1(
b00100 -
b00100 .
#680000000
0!
0(
#685000000
1!
b00101 '
1(
b00101 .
#690000000
0!
0(
#695000000
1!
b00110 '
1(
b00110 .
#700000000
0!
0(
#705000000
1!
1(
#710000000
0!
0(
#715000000
1!
b01000 &
b01000 '
1(
b01000 -
b01000 .
#720000000
0!
0(
#725000000
1!
1(
#730000000
0!
0(
#735000000
1!
1(
#740000000
0!
0(
#745000000
1!
1(
#750000000
0!
0(
#755000000
1!
1(
#760000000
0!
0(
#765000000
1!
b00100 &
b00100 '
1(
b00100 -
b00100 .
#770000000
0!
0(
#775000000
1!
b00101 '
1(
b00101 .
#780000000
0!
0(
#785000000
1!
b00110 '
1(
b00110 .
#790000000
0!
0(
#795000000
1!
1(
#800000000
0!
0(
#805000000
1!
b01000 &
b01000 '
1(
b01000 -
b01000 .
#810000000
0!
0(
#815000000
1!
1(
#820000000
0!
0(
#825000000
1!
1(
#830000000
0!
0(
#835000000
1!
1(
#840000000
0!
0(
#845000000
1!
1(
#850000000
0!
0(
#855000000
1!
b00100 &
b00100 '
1(
b00100 -
b00100 .
#860000000
0!
0(
#865000000
1!
b00101 '
1(
b00101 .
#870000000
0!
0(
#875000000
1!
b00110 '
1(
b00110 .
#880000000
0!
0(
#885000000
1!
1(
#890000000
0!
0(
#895000000
1!
b01000 &
b01000 '
1(
b01000 -
b01000 .
#900000000
0!
0(
#905000000
1!
1(
#910000000
0!
0(
#915000000
1!
1(
#920000000
0!
0(
#925000000
1!
1(
#930000000
0!
0(
#935000000
1!
1(
#940000000
0!
0(
#945000000
1!
b00100 &
b00100 '
1(
b00100 -
b00100 .
#950000000
0!
0(
#955000000
1!
b00101 '
1(
b00101 .
#960000000
0!
0(
#965000000
1!
b00110 '
1(
b00110 .
#970000000
0!
0(
#975000000
1!
1(
#980000000
0!
0(
#985000000
1!
b01000 &
b01000 '
1(
b01000 -
b01000 .
