HW2/q4/q4.vhdl
library IEEE;
use IEEE.NUMERIC_STD.ALL;
use IEEE.STD_LOGIC_1164.ALL;

entity bellClk is
    port(
        clk         : in  std_logic;
        reset       : in  std_logic;
        clock_set   : in  std_logic;
        alarm_set   : in  std_logic;
        alarm_stop  : in  std_logic;
        minute_in   : in std_logic_vector(7 downto 0);
        hour_in     : in std_logic_vector(5 downto 0);
        alarm_on    : out std_logic
    );
end entity bellClk;

architecture Behavioral of bellClk is
    signal second : integer       := 0;
    signal minute : integer       := 0;
    signal minute_alarm : integer := 0; 
    signal hour : integer         := 0;
    signal hour_alarm : integer   := 0;
begin
    process(clk, reset)
    begin
        if reset = '1' then
            second <= 0;
            minute <= 0;
            hour <= 0;
            alarm_on <= '0';
        elsif rising_edge(clk) then
            if clock_set = '1' then
                minute <= to_integer(unsigned(minute_in));
                hour <= to_integer(unsigned(hour_in));
            elsif alarm_set = '1' then
                minute_alarm <= to_integer(unsigned(minute_in));
                hour_alarm <= to_integer(unsigned(hour_in));
            else
                second <= second + 1;
                if second = 60 then
                    second <= 0;
                    minute <= minute + 1;
                end if;
                if minute = 60 then
                    minute <= 0;
                    hour <= hour + 1;
                end if;
                if hour = 24 then
                    hour <= 0;
                end if;

                if (hour = hour_alarm) and (minute = minute_alarm) then
                    alarm_on <= '1';
                elsif alarm_stop = '1' then
                    alarm_on <= '0';
                end if;
            end if;
        end if;

    end process;
end Behavioral;

HW2/q4/test4.vhdl
library IEEE;
use IEEE.NUMERIC_STD.ALL;
use IEEE.STD_LOGIC_1164.ALL;
entity test4 is
end test4;

architecture testbench of test4 is
    component bellClk is
        port(
            clk         : in  std_logic;
            reset       : in  std_logic;
            clock_set   : in  std_logic;
            alarm_set   : in  std_logic;
            alarm_stop  : in  std_logic;
            minute_in   : in std_logic_vector(7 downto 0);
            hour_in     : in std_logic_vector(5 downto 0);
            alarm_on    : out std_logic
        );
    end component;

    signal clk       : std_logic := '0';
    signal reset     : std_logic := '0';
    signal clock_set : std_logic := '0';
    signal alarm_set : std_logic := '0';
    signal alarm_stop: std_logic := '0';
    signal minute_in : std_logic_vector(7 downto 0);
    signal hour_in   : std_logic_vector(5 downto 0);
    signal alarm_on  : std_logic;

    constant CLOCK_PERIOD : time := 10 ns; 

begin
    cal : bellClk port map (
        clk         => clk,
        reset       => reset,
        clock_set   => clock_set,
        alarm_set   => alarm_set,
        alarm_stop  => alarm_stop,
        minute_in   => minute_in,
        hour_in     => hour_in,
        alarm_on    => alarm_on
        );

    clk_process: process
    begin
        while now < 1000 ns loop
            clk <= not clk;
            wait for CLOCK_PERIOD / 2;
        end loop;
        wait;
    end process;

    stimulus_process: process
    begin
        reset <= '1';
        wait for 10 ns;
        reset <= '0';

        -- Test clock set(3:19)
        clock_set <= '1';
        minute_in <= "00010011";
        hour_in   <= "000011";
        wait for 10 ns;
        clock_set <= '0';
        wait for 100 ns;
        
        -- Test alarm set(2:15)
        alarm_set <= '1';
        minute_in <= "00001111";
        hour_in   <= "000010";
        wait for 10 ns;
        alarm_set <= '0';
        wait for 100 ns;
        
        -- Test alarm alert
        alarm_stop <= '0';
        wait for 500 ns;
        alarm_stop <= '1';
        wait for 200 ns;
        wait;

    end process;

end testbench;

HW2/q4/out.vcd
$date
  Thu Jun  1 17:43:30 2023
$end
$version
  GHDL v0
$end
$timescale
  1 fs
$end
$scope module standard $end
$upscope $end
$scope module std_logic_1164 $end
$upscope $end
$scope module numeric_std $end
$upscope $end
$scope module test4 $end
$var reg 1 ! clk $end
$var reg 1 " reset $end
$var reg 1 # clock_set $end
$var reg 1 $ alarm_set $end
$var reg 1 % alarm_stop $end
$var reg 8 & minute_in[7:0] $end
$var reg 6 ' hour_in[5:0] $end
$var reg 1 ( alarm_on $end
$scope module cal $end
$var reg 1 ) clk $end
$var reg 1 * reset $end
$var reg 1 + clock_set $end
$var reg 1 , alarm_set $end
$var reg 1 - alarm_stop $end
$var reg 8 . minute_in[7:0] $end
$var reg 6 / hour_in[5:0] $end
$var reg 1 0 alarm_on $end
$var integer 32 1 second $end
$var integer 32 2 minute $end
$var integer 32 3 minute_alarm $end
$var integer 32 4 hour $end
$var integer 32 5 hour_alarm $end
$upscope $end
$upscope $end
$enddefinitions $end
#0
1!
1"
0#
0$
0%
bUUUUUUUU &
bUUUUUU '
0(
1)
1*
0+
0,
0-
bUUUUUUUU .
bUUUUUU /
00
b0 1
b0 2
b0 3
b0 4
b0 5
#5000000
0!
0)
#10000000
1!
0"
1#
b00010011 &
b000011 '
1)
0*
1+
b00010011 .
b000011 /
b10011 2
b11 4
#15000000
0!
0)
#20000000
1!
0#
1)
0+
b1 1
#25000000
0!
0)
#30000000
1!
1)
b10 1
#35000000
0!
0)
#40000000
1!
1)
b11 1
#45000000
0!
0)
#50000000
1!
1)
b100 1
#55000000
0!
0)
#60000000
1!
1)
b101 1
#65000000
0!
0)
#70000000
1!
1)
b110 1
#75000000
0!
0)
#80000000
1!
1)
b111 1
#85000000
0!
0)
#90000000
1!
1)
b1000 1
#95000000
0!
0)
#100000000
1!
1)
b1001 1
#105000000
0!
0)
#110000000
1!
1)
b1010 1
#115000000
0!
0)
#120000000
1!
1$
b00001111 &
b000010 '
1)
1,
b00001111 .
b000010 /
b1111 3
b10 5
#125000000
0!
0)
#130000000
1!
0$
1)
0,
b1011 1
#135000000
0!
0)
#140000000
1!
1)
b1100 1
#145000000
0!
0)
#150000000
1!
1)
b1101 1
#155000000
0!
0)
#160000000
1!
1)
b1110 1
#165000000
0!
0)
#170000000
1!
1)
b1111 1
#175000000
0!
0)
#180000000
1!
1)
b10000 1
#185000000
0!
0)
#190000000
1!
1)
b10001 1
#195000000
0!
0)
#200000000
1!
1)
b10010 1
#205000000
0!
0)
#210000000
1!
1)
b10011 1
#215000000
0!
0)
#220000000
1!
1)
b10100 1
#225000000
0!
0)
#230000000
1!
1)
b10101 1
#235000000
0!
0)
#240000000
1!
1)
b10110 1
#245000000
0!
0)
#250000000
1!
1)
b10111 1
#255000000
0!
0)
#260000000
1!
1)
b11000 1
#265000000
0!
0)
#270000000
1!
1)
b11001 1
#275000000
0!
0)
#280000000
1!
1)
b11010 1
#285000000
0!
0)
#290000000
1!
1)
b11011 1
#295000000
0!
0)
#300000000
1!
1)
b11100 1
#305000000
0!
0)
#310000000
1!
1)
b11101 1
#315000000
0!
0)
#320000000
1!
1)
b11110 1
#325000000
0!
0)
#330000000
1!
1)
b11111 1
#335000000
0!
0)
#340000000
1!
1)
b100000 1
#345000000
0!
0)
#350000000
1!
1)
b100001 1
#355000000
0!
0)
#360000000
1!
1)
b100010 1
#365000000
0!
0)
#370000000
1!
1)
b100011 1
#375000000
0!
0)
#380000000
1!
1)
b100100 1
#385000000
0!
0)
#390000000
1!
1)
b100101 1
#395000000
0!
0)
#400000000
1!
1)
b100110 1
#405000000
0!
0)
#410000000
1!
1)
b100111 1
#415000000
0!
0)
#420000000
1!
1)
b101000 1
#425000000
0!
0)
#430000000
1!
1)
b101001 1
#435000000
0!
0)
#440000000
1!
1)
b101010 1
#445000000
0!
0)
#450000000
1!
1)
b101011 1
#455000000
0!
0)
#460000000
1!
1)
b101100 1
#465000000
0!
0)
#470000000
1!
1)
b101101 1
#475000000
0!
0)
#480000000
1!
1)
b101110 1
#485000000
0!
0)
#490000000
1!
1)
b101111 1
#495000000
0!
0)
#500000000
1!
1)
b110000 1
#505000000
0!
0)
#510000000
1!
1)
b110001 1
#515000000
0!
0)
#520000000
1!
1)
b110010 1
#525000000
0!
0)
#530000000
1!
1)
b110011 1
#535000000
0!
0)
#540000000
1!
1)
b110100 1
#545000000
0!
0)
#550000000
1!
1)
b110101 1
#555000000
0!
0)
#560000000
1!
1)
b110110 1
#565000000
0!
0)
#570000000
1!
1)
b110111 1
#575000000
0!
0)
#580000000
1!
1)
b111000 1
#585000000
0!
0)
#590000000
1!
1)
b111001 1
#595000000
0!
0)
#600000000
1!
1)
b111010 1
#605000000
0!
0)
#610000000
1!
1)
b111011 1
#615000000
0!
0)
#620000000
1!
1)
b111100 1
#625000000
0!
0)
#630000000
1!
1)
b0 1
b10100 2
#635000000
0!
0)
#640000000
1!
1)
b1 1
#645000000
0!
0)
#650000000
1!
1)
b10 1
#655000000
0!
0)
#660000000
1!
1)
b11 1
#665000000
0!
0)
#670000000
1!
1)
b100 1
#675000000
0!
0)
#680000000
1!
1)
b101 1
#685000000
0!
0)
#690000000
1!
1)
b110 1
#695000000
0!
0)
#700000000
1!
1)
b111 1
#705000000
0!
0)
#710000000
1!
1)
b1000 1
#715000000
0!
0)
#720000000
1!
1)
b1001 1
#725000000
0!
0)
#730000000
1!
1%
1)
1-
b1010 1
#735000000
0!
0)
#740000000
1!
1)
b1011 1
#745000000
0!
0)
#750000000
1!
1)
b1100 1
#755000000
0!
0)
#760000000
1!
1)
b1101 1
#765000000
0!
0)
#770000000
1!
1)
b1110 1
#775000000
0!
0)
#780000000
1!
1)
b1111 1
#785000000
0!
0)
#790000000
1!
1)
b10000 1
#795000000
0!
0)
#800000000
1!
1)
b10001 1
#805000000
0!
0)
#810000000
1!
1)
b10010 1
#815000000
0!
0)
#820000000
1!
1)
b10011 1
#825000000
0!
0)
#830000000
1!
1)
b10100 1
#835000000
0!
0)
#840000000
1!
1)
b10101 1
#845000000
0!
0)
#850000000
1!
1)
b10110 1
#855000000
0!
0)
#860000000
1!
1)
b10111 1
#865000000
0!
0)
#870000000
1!
1)
b11000 1
#875000000
0!
0)
#880000000
1!
1)
b11001 1
#885000000
0!
0)
#890000000
1!
1)
b11010 1
#895000000
0!
0)
#900000000
1!
1)
b11011 1
#905000000
0!
0)
#910000000
1!
1)
b11100 1
#915000000
0!
0)
#920000000
1!
1)
b11101 1
#925000000
0!
0)
#930000000
1!
1)
b11110 1
#935000000
0!
0)
#940000000
1!
1)
b11111 1
#945000000
0!
0)
#950000000
1!
1)
b100000 1
#955000000
0!
0)
#960000000
1!
1)
b100001 1
#965000000
0!
0)
#970000000
1!
1)
b100010 1
#975000000
0!
0)
#980000000
1!
1)
b100011 1
#985000000
0!
0)
#990000000
1!
1)
b100100 1
