state_machine_project/state_machine.vhd
library IEEE;
use IEEE.std_logic_1164.all;
use IEEE.std_logic_arith.all;
use IEEE.std_logic_unsigned.all;

entity lift_ctr is 
	port (    
		button   : in STD_LOGIC;
		clk      : in STD_LOGIC;
		dco_s    : in STD_LOGIC;
		go_down  : in STD_LOGIC;
		go_up    : in STD_LOGIC;
		dco      : out STD_LOGIC;
		fan      : out STD_LOGIC;
		motor    : out STD_LOGIC;
		motor_dir: out STD_LOGIC
		);
end lift_ctr;

architecture lift_ctr_arch of lift_ctr is
attribute enum_encoding: string;
type State_type is  (Ground, starting_up, going_up,  Top,  starting_down, going_down );

attribute enum_encoding of State_type: type is
	"000 " &		-- Ground
	"001 " &		-- starting_up
	"010 " &		-- going_up
	"011 " &		-- Top
	"100 " &		-- starting_down
	"101" ; 		-- going_down
signal State: State_type;
begin
State_machine: process (clk)
begin
	if clk'event and clk = '1' then
		case State is
			when Ground =>
				dco <= '0';
				fan <= '0';
				motor <= '0';
				if button = '1' then	
					State <= starting_up;
				elsif button = '0' then	
					State <= Ground;
				end if;
			when starting_up =>
				fan <= '1';
				dco <= '1';
				motor_dir <= '1';
				if dco_s = '1' then	
					State <= going_up;
				elsif dco_s = '0' then	
					State <= starting_up;
				end if;
			when going_up =>
				motor <= '1';
				fan <= '1';
				if go_up = '1' then	
					State <= Top;
				elsif go_up = '0' then	
					State <= going_up;
				end if;
			when Top =>
				dco <= '0';
				fan <= '0';
				motor <= '0';
				if button = '1' then	
					State <= starting_down;
				elsif button = '0' then	
					State <= Top;
				end if;
			when starting_down =>
				fan <= '1';
				dco <= '1';
				motor_dir <= '0';
				if dco_s = '1' then	
					State <= going_down;
				elsif dco_s = '0' then	
					State <= starting_down;
				end if;
			when going_down =>
				motor <= '1';
				fan <= '1';
				if go_down = '1' then	
					State <= Ground;
				elsif go_down = '0' then	
					State <= going_down;
				end if;
		end case;
	end if;
end process;
end lift_ctr_arch;

state_machine_project/test_state.vhd
library IEEE;
use IEEE.std_logic_1164.all;

entity lift_ctr_tb is
end lift_ctr_tb;

architecture testbench of lift_ctr_tb is
    -- Constants
    constant CLK_PERIOD: time := 10 ns;
    
    -- Component declaration
    component lift_ctr is
        port (
            button: in std_logic;
            clk: in std_logic;
            dco_s: in std_logic;
            go_down: in std_logic;
            go_up: in std_logic;
            dco: out std_logic;
            fan: out std_logic;
            motor: out std_logic;
            motor_dir: out std_logic
        );
    end component;
    
    -- Signals
    signal button_tb: std_logic := '0';
    signal clk_tb: std_logic := '0';
    signal dco_s_tb: std_logic := '0';
    signal go_down_tb: std_logic := '0';
    signal go_up_tb: std_logic := '0';
    signal dco_tb: std_logic;
    signal fan_tb: std_logic;
    signal motor_tb: std_logic;
    signal motor_dir_tb: std_logic;
    
begin
    -- Instantiate the lift_ctr module
    dut: lift_ctr
        port map (
            button => button_tb,
            clk => clk_tb,
            dco_s => dco_s_tb,
            go_down => go_down_tb,
            go_up => go_up_tb,
            dco => dco_tb,
            fan => fan_tb,
            motor => motor_tb,
            motor_dir => motor_dir_tb
        );
        
    -- Clock process
    clk_process: process
    begin
        while now < 1000 ns loop
            clk_tb <= '0';
            wait for CLK_PERIOD / 2;
            clk_tb <= '1';
            wait for CLK_PERIOD / 2;
        end loop;
        wait;
    end process;
    
    stimulus_process: process
    begin

        button_tb <= '0';
        wait for 10 ns;


        button_tb <= '1';
        dco_s_tb <= '0';
        wait for 20 ns;

        dco_s_tb <= '1';
        go_up_tb <= '0';
        wait for 20 ns;

        go_up_tb <= '1';
        button_tb <= '0';
        wait for 20 ns;


        button_tb <= '1';
        dco_s_tb <= '0';
        wait for 20 ns;


        dco_s_tb <= '1';
        go_down_tb <= '0';
        wait for 20 ns;


        go_down_tb <= '1';
        button_tb <= '0';
        wait for 20 ns;

        wait;
    end process;
    
end testbench;

state_machine_project/out.vcd
$date
  Sun Jun 25 15:43:37 2023
$end
$version
  GHDL v0
$end
$timescale
  1 fs
$end
$scope module standard $end
$upscope $end
$scope module std_logic_1164 $end
$upscope $end
$scope module std_logic_arith $end
$upscope $end
$scope module std_logic_unsigned $end
$upscope $end
$scope module lift_ctr_tb $end
$var reg 1 ! button_tb $end
$var reg 1 " clk_tb $end
$var reg 1 # dco_s_tb $end
$var reg 1 $ go_down_tb $end
$var reg 1 % go_up_tb $end
$var reg 1 & dco_tb $end
$var reg 1 ' fan_tb $end
$var reg 1 ( motor_tb $end
$var reg 1 ) motor_dir_tb $end
$scope module dut $end
$var reg 1 * button $end
$var reg 1 + clk $end
$var reg 1 , dco_s $end
$var reg 1 - go_down $end
$var reg 1 . go_up $end
$var reg 1 / dco $end
$var reg 1 0 fan $end
$var reg 1 1 motor $end
$var reg 1 2 motor_dir $end
$comment state is not handled $end
$upscope $end
$upscope $end
$enddefinitions $end
#0
0!
0"
0#
0$
0%
U&
U'
U(
U)
0*
0+
0,
0-
0.
U/
U0
U1
U2
#5000000
1"
0&
0'
0(
1+
0/
00
01
#10000000
1!
0"
1*
0+
#15000000
1"
1+
#20000000
0"
0+
#25000000
1"
1&
1'
1)
1+
1/
10
12
#30000000
0"
1#
0+
1,
#35000000
1"
1+
#40000000
0"
0+
#45000000
1"
1(
1+
11
#50000000
0!
0"
1%
0*
0+
1.
#55000000
1"
1+
#60000000
0"
0+
#65000000
1"
0&
0'
0(
1+
0/
00
01
#70000000
1!
0"
0#
1*
0+
0,
#75000000
1"
1+
#80000000
0"
0+
#85000000
1"
1&
1'
0)
1+
1/
10
02
#90000000
0"
1#
0+
1,
#95000000
1"
1+
#100000000
0"
0+
#105000000
1"
1(
1+
11
#110000000
0!
0"
1$
0*
0+
1-
#115000000
1"
1+
#120000000
0"
0+
#125000000
1"
0&
0'
0(
1+
0/
00
01
